Workbook

Sheet Instrucciones
B2: Los números del centro · Centro de Excelencia Implantológica Alma
B3: Instrumento del apartado 7 y del apartado 13 del Plan de Dirección v28.0 · Ejercicio 2026
B5: Para qué sirve | C5: El Plan de Dirección declara que el centro no dispone todavía de sus cinco números ni de serie propia en ninguno de los diez indicadores. Este libro es el instrumento para conseguirlos: se rellena una hoja al mes y el resumen anual y el semáforo se calculan solos.
B6: Qué se teclea | C6: Solo las celdas con fondo amarillo y cifra azul. Todo lo demás son fórmulas: no se sobrescriben.
B7: Código de color | C7: Azul sobre amarillo = dato que introduce el centro · Negro = calculado · Verde = viene de otra hoja.
B8: La regla de reporte | C8: Un indicador sin dato se reporta en rojo, no en blanco. El semáforo lo hace automáticamente: mientras no haya cifra, la casilla dice SIN DATO y cuenta como roja en la revisión de Junta.
B9: El indicador 6 | C9: Tiene cohorte cerrada: el dato de un mes no es definitivo hasta sesenta días después. Se anota provisional y se corrige en la revisión siguiente. La columna «Estado del dato» sirve para eso.
B10: Umbrales | C10: Están en la hoja Definiciones y son supuestos de trabajo, no objetivos aprobados. Se cambian ahí una sola vez y todas las hojas mensuales los recogen.
B11: Los cinco números | C11: Tienen hoja propia. Son la prioridad: sin ellos cualquier objetivo comercial es una opinión.
B12: Ejemplo | C12: La hoja «01 Enero» viene con una fila de ejemplo en gris al pie, para mostrar el formato esperado. Bórrese antes de usarla.
B14: Hojas del libro
B15: Definiciones | C15: El diccionario de los diez indicadores y los umbrales editables
B16: 01 a 12 · meses | C16: Una hoja de captura por mes, con semáforo automático
B17: Resumen anual | C17: Los doce meses en una sola rejilla, con tendencia y meses con dato
B18: Los cinco números | C18: Costes fijos, equilibrio, primeras visitas necesarias, producto pendiente y colchón

Sheet Definiciones
A1: Diccionario de indicadores
A2: Definición operativa acordada. Cambiar aquí un umbral lo cambia en las doce hojas mensuales. Los umbrales son supuestos de trabajo, no objetivos aprobados por la Junta.
A4: # | B4: Indicador | C4: Numerador | D4: Denominador | E4: Umbral publicado | F4: Sentido | G4: Verde si | H4: Ámbar si | I4: Qué queda fuera
A5: 1 | B5: Verificaciones regulatorias cerradas | C5: Verificaciones V1–V11 con evidencia archivada | D5: 11 (fijo) | E5: 11 de 11 | F5: mayor | G5: 1 | H5: 0.8 | I5: Nada: una verificación en trámite cuenta como no cerrada
A6: 2 | B6: Bajas voluntarias del equipo | C6: Ceses a instancia de la persona trabajadora | D6: Plantilla media del mes | E6: 0 | F6: menor | G6: 0.0001 | H6: 0.05 | I6: Fin de contrato temporal previsto e incapacidades temporales
A7: 3 | B7: Reclamaciones de pacientes heredados | C7: Reclamaciones formales del mes | D7: — | E7: 0 | F7: menor | G7: 0.0001 | H7: 1 | I7: Quejas verbales resueltas en el acto y registradas como incidencia de nivel 1
A8: 4 | B8: Documentación digitalizada el mismo día | C8: Actos con historia, consentimiento e imágenes en el día | D8: Actos clínicos del día | E8: 100 % | F8: mayor | G8: 0.98 | H8: 0.9 | I8: Nada
A9: 5 | B9: Producto pendiente | C9: Importe aceptado y no terminado a fin de mes | D9: — | E9: Descendente | F9: descendente | G9: 0 | H9: 0 | I9: Presupuestos presentados y no aceptados
A10: 6 | B10: Tasa de conversión de la primera visita | C10: PV del mes aceptadas y pagadas en 60 días | D10: Primeras visitas del mes | E10: Línea base y mejora | F10: mayor | G10: 0.45 | H10: 0.35 | I10: Urgencias, segundas opiniones y derivaciones a otro centro por criterio clínico
A11: 7 | B11: Pacientes en mantenimiento activo | C11: Con revisión en 12 meses y próxima cita agendada | D11: Pacientes con implantes del centro | E11: Creciente | F11: mayor | G11: 0.6 | H11: 0.4 | I11: Pacientes con cita agendada pero sin ninguna asistencia en 12 meses
A12: 8 | B12: Captación por recomendación | C12: PV cuyo origen declarado es la recomendación | D12: Primeras visitas del mes | E12: Creciente | F12: mayor | G12: 0.3 | H12: 0.2 | I12: Nada: el origen «no consta» permanece en el denominador
A13: 9 | B13: Ofrecimiento del programa de cuidado | C13: Cierres con ofrecimiento registrado | D13: Cierres de tratamiento del mes | E13: 90 % | F13: mayor | G13: 0.9 | H13: 0.8 | I13: Nada: se mide el ofrecimiento, no la contratación
A14: 10 | B14: Auditorías ejecutadas en fecha | C14: Auditorías realizadas con resultado registrado | D14: Auditorías programadas | E14: 100 % | F14: mayor | G14: 1 | H14: 0.5 | I14: Nada: una auditoría sin registro cuenta como no realizada
A16: Los umbrales de las columnas G y H son los únicos valores editables de esta hoja.

Sheet 01 Enero
A1: Captura mensual · Enero de 2026
A2: Rellénense únicamente las casillas amarillas. El resultado y el semáforo se calculan solos.
A4: # | B4: Indicador | C4: Numerador | D4: Denominador | E4: Resultado | F4: Umbral | G4: Estado | H4: Estado del dato | I4: Notas
A6: 1 | B6: Verificaciones regulatorias cerradas | D6: 11 | E6: =IF(OR(C6="",D6="",D6=0),"",C6/D6) | F6: 11 de 11 | G6: =IF(C6="","SIN DATO",IF(E6>=Definiciones!$G$5,"VERDE",IF(E6>=Definiciones!$H$5,"ÁMBAR","ROJO"))) -> SIN DATO
A7: 2 | B7: Bajas voluntarias del equipo | E7: =IF(OR(C7="",D7="",D7=0),"",C7/D7) | F7: 0 | G7: =IF(C7="","SIN DATO",IF(E7<=Definiciones!$G$6,"VERDE",IF(E7<=Definiciones!$H$6,"ÁMBAR","ROJO"))) -> SIN DATO
A8: 3 | B8: Reclamaciones de pacientes heredados | D8: — | E8: =IF(C8="","",C8) | F8: 0 | G8: =IF(C8="","SIN DATO",IF(E8<=Definiciones!$G$7,"VERDE",IF(E8<=Definiciones!$H$7,"ÁMBAR","ROJO"))) -> SIN DATO
A9: 4 | B9: Documentación digitalizada el mismo día | E9: =IF(OR(C9="",D9="",D9=0),"",C9/D9) | F9: 100 % | G9: =IF(C9="","SIN DATO",IF(E9>=Definiciones!$G$8,"VERDE",IF(E9>=Definiciones!$H$8,"ÁMBAR","ROJO"))) -> SIN DATO
A10: 5 | B10: Producto pendiente | D10: — | E10: =IF(C10="","",C10) | F10: Descendente | G10: =IF(C10="","SIN DATO","COMPARAR") -> SIN DATO
A11: 6 | B11: Tasa de conversión de la primera visita | E11: =IF(OR(C11="",D11="",D11=0),"",C11/D11) | F11: Línea base y mejora | G11: =IF(C11="","SIN DATO",IF(E11>=Definiciones!$G$10,"VERDE",IF(E11>=Definiciones!$H$10,"ÁMBAR","ROJO"))) -> SIN DATO
A12: 7 | B12: Pacientes en mantenimiento activo | E12: =IF(OR(C12="",D12="",D12=0),"",C12/D12) | F12: Creciente | G12: =IF(C12="","SIN DATO",IF(E12>=Definiciones!$G$11,"VERDE",IF(E12>=Definiciones!$H$11,"ÁMBAR","ROJO"))) -> SIN DATO | H12: Provisional
A13: 8 | B13: Captación por recomendación | E13: =IF(OR(C13="",D13="",D13=0),"",C13/D13) | F13: Creciente | G13: =IF(C13="","SIN DATO",IF(E13>=Definiciones!$G$12,"VERDE",IF(E13>=Definiciones!$H$12,"ÁMBAR","ROJO"))) -> SIN DATO
A14: 9 | B14: Ofrecimiento del programa de cuidado | E14: =IF(OR(C14="",D14="",D14=0),"",C14/D14) | F14: 90 % | G14: =IF(C14="","SIN DATO",IF(E14>=Definiciones!$G$13,"VERDE",IF(E14>=Definiciones!$H$13,"ÁMBAR","ROJO"))) -> SIN DATO
A15: 10 | B15: Auditorías ejecutadas en fecha | E15: =IF(OR(C15="",D15="",D15=0),"",C15/D15) | F15: 100 % | G15: =IF(C15="","SIN DATO",IF(E15>=Definiciones!$G$14,"VERDE",IF(E15>=Definiciones!$H$14,"ÁMBAR","ROJO"))) -> SIN DATO
B17: El indicador 5 se compara con el mes anterior: la casilla dice COMPARAR porque el sentido «descendente» exige mirar la serie, no un umbral fijo.
B18: Un indicador en SIN DATO cuenta como rojo en la revisión de Junta.
B20: EJEMPLO — bórrese antes de usar la hoja
A21: 6 | B21: Tasa de conversión de la primera visita | C21: 38 | D21: 84 | E21: =IF(OR(C21="",D21=""),"",C21/D21) -> 0.45238095 | I21: 38 de 84 primeras visitas aceptadas y pagadas dentro de los 60 días

Sheet 02 Febrero
A1: Captura mensual · Febrero de 2026
A2: Rellénense únicamente las casillas amarillas. El resultado y el semáforo se calculan solos.
A4: # | B4: Indicador | C4: Numerador | D4: Denominador | E4: Resultado | F4: Umbral | G4: Estado | H4: Estado del dato | I4: Notas
A6: 1 | B6: Verificaciones regulatorias cerradas | D6: 11 | E6: =IF(OR(C6="",D6="",D6=0),"",C6/D6) | F6: 11 de 11 | G6: =IF(C6="","SIN DATO",IF(E6>=Definiciones!$G$5,"VERDE",IF(E6>=Definiciones!$H$5,"ÁMBAR","ROJO"))) -> SIN DATO
A7: 2 | B7: Bajas voluntarias del equipo | E7: =IF(OR(C7="",D7="",D7=0),"",C7/D7) | F7: 0 | G7: =IF(C7="","SIN DATO",IF(E7<=Definiciones!$G$6,"VERDE",IF(E7<=Definiciones!$H$6,"ÁMBAR","ROJO"))) -> SIN DATO
A8: 3 | B8: Reclamaciones de pacientes heredados | D8: — | E8: =IF(C8="","",C8) | F8: 0 | G8: =IF(C8="","SIN DATO",IF(E8<=Definiciones!$G$7,"VERDE",IF(E8<=Definiciones!$H$7,"ÁMBAR","ROJO"))) -> SIN DATO
A9: 4 | B9: Documentación digitalizada el mismo día | E9: =IF(OR(C9="",D9="",D9=0),"",C9/D9) | F9: 100 % | G9: =IF(C9="","SIN DATO",IF(E9>=Definiciones!$G$8,"VERDE",IF(E9>=Definiciones!$H$8,"ÁMBAR","ROJO"))) -> SIN DATO
A10: 5 | B10: Producto pendiente | D10: — | E10: =IF(C10="","",C10) | F10: Descendente | G10: =IF(C10="","SIN DATO","COMPARAR") -> SIN DATO
A11: 6 | B11: Tasa de conversión de la primera visita | E11: =IF(OR(C11="",D11="",D11=0),"",C11/D11) | F11: Línea base y mejora | G11: =IF(C11="","SIN DATO",IF(E11>=Definiciones!$G$10,"VERDE",IF(E11>=Definiciones!$H$10,"ÁMBAR","ROJO"))) -> SIN DATO
A12: 7 | B12: Pacientes en mantenimiento activo | E12: =IF(OR(C12="",D12="",D12=0),"",C12/D12) | F12: Creciente | G12: =IF(C12="","SIN DATO",IF(E12>=Definiciones!$G$11,"VERDE",IF(E12>=Definiciones!$H$11,"ÁMBAR","ROJO"))) -> SIN DATO | H12: Provisional
A13: 8 | B13: Captación por recomendación | E13: =IF(OR(C13="",D13="",D13=0),"",C13/D13) | F13: Creciente | G13: =IF(C13="","SIN DATO",IF(E13>=Definiciones!$G$12,"VERDE",IF(E13>=Definiciones!$H$12,"ÁMBAR","ROJO"))) -> SIN DATO
A14: 9 | B14: Ofrecimiento del programa de cuidado | E14: =IF(OR(C14="",D14="",D14=0),"",C14/D14) | F14: 90 % | G14: =IF(C14="","SIN DATO",IF(E14>=Definiciones!$G$13,"VERDE",IF(E14>=Definiciones!$H$13,"ÁMBAR","ROJO"))) -> SIN DATO
A15: 10 | B15: Auditorías ejecutadas en fecha | E15: =IF(OR(C15="",D15="",D15=0),"",C15/D15) | F15: 100 % | G15: =IF(C15="","SIN DATO",IF(E15>=Definiciones!$G$14,"VERDE",IF(E15>=Definiciones!$H$14,"ÁMBAR","ROJO"))) -> SIN DATO
B17: El indicador 5 se compara con el mes anterior: la casilla dice COMPARAR porque el sentido «descendente» exige mirar la serie, no un umbral fijo.
B18: Un indicador en SIN DATO cuenta como rojo en la revisión de Junta.

Sheet 03 Marzo
A1: Captura mensual · Marzo de 2026
A2: Rellénense únicamente las casillas amarillas. El resultado y el semáforo se calculan solos.
A4: # | B4: Indicador | C4: Numerador | D4: Denominador | E4: Resultado | F4: Umbral | G4: Estado | H4: Estado del dato | I4: Notas
A6: 1 | B6: Verificaciones regulatorias cerradas | D6: 11 | E6: =IF(OR(C6="",D6="",D6=0),"",C6/D6) | F6: 11 de 11 | G6: =IF(C6="","SIN DATO",IF(E6>=Definiciones!$G$5,"VERDE",IF(E6>=Definiciones!$H$5,"ÁMBAR","ROJO"))) -> SIN DATO
A7: 2 | B7: Bajas voluntarias del equipo | E7: =IF(OR(C7="",D7="",D7=0),"",C7/D7) | F7: 0 | G7: =IF(C7="","SIN DATO",IF(E7<=Definiciones!$G$6,"VERDE",IF(E7<=Definiciones!$H$6,"ÁMBAR","ROJO"))) -> SIN DATO
A8: 3 | B8: Reclamaciones de pacientes heredados | D8: — | E8: =IF(C8="","",C8) | F8: 0 | G8: =IF(C8="","SIN DATO",IF(E8<=Definiciones!$G$7,"VERDE",IF(E8<=Definiciones!$H$7,"ÁMBAR","ROJO"))) -> SIN DATO
A9: 4 | B9: Documentación digitalizada el mismo día | E9: =IF(OR(C9="",D9="",D9=0),"",C9/D9) | F9: 100 % | G9: =IF(C9="","SIN DATO",IF(E9>=Definiciones!$G$8,"VERDE",IF(E9>=Definiciones!$H$8,"ÁMBAR","ROJO"))) -> SIN DATO
A10: 5 | B10: Producto pendiente | D10: — | E10: =IF(C10="","",C10) | F10: Descendente | G10: =IF(C10="","SIN DATO","COMPARAR") -> SIN DATO
A11: 6 | B11: Tasa de conversión de la primera visita | E11: =IF(OR(C11="",D11="",D11=0),"",C11/D11) | F11: Línea base y mejora | G11: =IF(C11="","SIN DATO",IF(E11>=Definiciones!$G$10,"VERDE",IF(E11>=Definiciones!$H$10,"ÁMBAR","ROJO"))) -> SIN DATO
A12: 7 | B12: Pacientes en mantenimiento activo | E12: =IF(OR(C12="",D12="",D12=0),"",C12/D12) | F12: Creciente | G12: =IF(C12="","SIN DATO",IF(E12>=Definiciones!$G$11,"VERDE",IF(E12>=Definiciones!$H$11,"ÁMBAR","ROJO"))) -> SIN DATO | H12: Provisional
A13: 8 | B13: Captación por recomendación | E13: =IF(OR(C13="",D13="",D13=0),"",C13/D13) | F13: Creciente | G13: =IF(C13="","SIN DATO",IF(E13>=Definiciones!$G$12,"VERDE",IF(E13>=Definiciones!$H$12,"ÁMBAR","ROJO"))) -> SIN DATO
A14: 9 | B14: Ofrecimiento del programa de cuidado | E14: =IF(OR(C14="",D14="",D14=0),"",C14/D14) | F14: 90 % | G14: =IF(C14="","SIN DATO",IF(E14>=Definiciones!$G$13,"VERDE",IF(E14>=Definiciones!$H$13,"ÁMBAR","ROJO"))) -> SIN DATO
A15: 10 | B15: Auditorías ejecutadas en fecha | E15: =IF(OR(C15="",D15="",D15=0),"",C15/D15) | F15: 100 % | G15: =IF(C15="","SIN DATO",IF(E15>=Definiciones!$G$14,"VERDE",IF(E15>=Definiciones!$H$14,"ÁMBAR","ROJO"))) -> SIN DATO
B17: El indicador 5 se compara con el mes anterior: la casilla dice COMPARAR porque el sentido «descendente» exige mirar la serie, no un umbral fijo.
B18: Un indicador en SIN DATO cuenta como rojo en la revisión de Junta.

Sheet 04 Abril
A1: Captura mensual · Abril de 2026
A2: Rellénense únicamente las casillas amarillas. El resultado y el semáforo se calculan solos.
A4: # | B4: Indicador | C4: Numerador | D4: Denominador | E4: Resultado | F4: Umbral | G4: Estado | H4: Estado del dato | I4: Notas
A6: 1 | B6: Verificaciones regulatorias cerradas | D6: 11 | E6: =IF(OR(C6="",D6="",D6=0),"",C6/D6) | F6: 11 de 11 | G6: =IF(C6="","SIN DATO",IF(E6>=Definiciones!$G$5,"VERDE",IF(E6>=Definiciones!$H$5,"ÁMBAR","ROJO"))) -> SIN DATO
A7: 2 | B7: Bajas voluntarias del equipo | E7: =IF(OR(C7="",D7="",D7=0),"",C7/D7) | F7: 0 | G7: =IF(C7="","SIN DATO",IF(E7<=Definiciones!$G$6,"VERDE",IF(E7<=Definiciones!$H$6,"ÁMBAR","ROJO"))) -> SIN DATO
A8: 3 | B8: Reclamaciones de pacientes heredados | D8: — | E8: =IF(C8="","",C8) | F8: 0 | G8: =IF(C8="","SIN DATO",IF(E8<=Definiciones!$G$7,"VERDE",IF(E8<=Definiciones!$H$7,"ÁMBAR","ROJO"))) -> SIN DATO
A9: 4 | B9: Documentación digitalizada el mismo día | E9: =IF(OR(C9="",D9="",D9=0),"",C9/D9) | F9: 100 % | G9: =IF(C9="","SIN DATO",IF(E9>=Definiciones!$G$8,"VERDE",IF(E9>=Definiciones!$H$8,"ÁMBAR","ROJO"))) -> SIN DATO
A10: 5 | B10: Producto pendiente | D10: — | E10: =IF(C10="","",C10) | F10: Descendente | G10: =IF(C10="","SIN DATO","COMPARAR") -> SIN DATO
A11: 6 | B11: Tasa de conversión de la primera visita | E11: =IF(OR(C11="",D11="",D11=0),"",C11/D11) | F11: Línea base y mejora | G11: =IF(C11="","SIN DATO",IF(E11>=Definiciones!$G$10,"VERDE",IF(E11>=Definiciones!$H$10,"ÁMBAR","ROJO"))) -> SIN DATO
A12: 7 | B12: Pacientes en mantenimiento activo | E12: =IF(OR(C12="",D12="",D12=0),"",C12/D12) | F12: Creciente | G12: =IF(C12="","SIN DATO",IF(E12>=Definiciones!$G$11,"VERDE",IF(E12>=Definiciones!$H$11,"ÁMBAR","ROJO"))) -> SIN DATO | H12: Provisional
A13: 8 | B13: Captación por recomendación | E13: =IF(OR(C13="",D13="",D13=0),"",C13/D13) | F13: Creciente | G13: =IF(C13="","SIN DATO",IF(E13>=Definiciones!$G$12,"VERDE",IF(E13>=Definiciones!$H$12,"ÁMBAR","ROJO"))) -> SIN DATO
A14: 9 | B14: Ofrecimiento del programa de cuidado | E14: =IF(OR(C14="",D14="",D14=0),"",C14/D14) | F14: 90 % | G14: =IF(C14="","SIN DATO",IF(E14>=Definiciones!$G$13,"VERDE",IF(E14>=Definiciones!$H$13,"ÁMBAR","ROJO"))) -> SIN DATO
A15: 10 | B15: Auditorías ejecutadas en fecha | E15: =IF(OR(C15="",D15="",D15=0),"",C15/D15) | F15: 100 % | G15: =IF(C15="","SIN DATO",IF(E15>=Definiciones!$G$14,"VERDE",IF(E15>=Definiciones!$H$14,"ÁMBAR","ROJO"))) -> SIN DATO
B17: El indicador 5 se compara con el mes anterior: la casilla dice COMPARAR porque el sentido «descendente» exige mirar la serie, no un umbral fijo.
B18: Un indicador en SIN DATO cuenta como rojo en la revisión de Junta.

Sheet 05 Mayo
A1: Captura mensual · Mayo de 2026
A2: Rellénense únicamente las casillas amarillas. El resultado y el semáforo se calculan solos.
A4: # | B4: Indicador | C4: Numerador | D4: Denominador | E4: Resultado | F4: Umbral | G4: Estado | H4: Estado del dato | I4: Notas
A6: 1 | B6: Verificaciones regulatorias cerradas | D6: 11 | E6: =IF(OR(C6="",D6="",D6=0),"",C6/D6) | F6: 11 de 11 | G6: =IF(C6="","SIN DATO",IF(E6>=Definiciones!$G$5,"VERDE",IF(E6>=Definiciones!$H$5,"ÁMBAR","ROJO"))) -> SIN DATO
A7: 2 | B7: Bajas voluntarias del equipo | E7: =IF(OR(C7="",D7="",D7=0),"",C7/D7) | F7: 0 | G7: =IF(C7="","SIN DATO",IF(E7<=Definiciones!$G$6,"VERDE",IF(E7<=Definiciones!$H$6,"ÁMBAR","ROJO"))) -> SIN DATO
A8: 3 | B8: Reclamaciones de pacientes heredados | D8: — | E8: =IF(C8="","",C8) | F8: 0 | G8: =IF(C8="","SIN DATO",IF(E8<=Definiciones!$G$7,"VERDE",IF(E8<=Definiciones!$H$7,"ÁMBAR","ROJO"))) -> SIN DATO
A9: 4 | B9: Documentación digitalizada el mismo día | E9: =IF(OR(C9="",D9="",D9=0),"",C9/D9) | F9: 100 % | G9: =IF(C9="","SIN DATO",IF(E9>=Definiciones!$G$8,"VERDE",IF(E9>=Definiciones!$H$8,"ÁMBAR","ROJO"))) -> SIN DATO
A10: 5 | B10: Producto pendiente | D10: — | E10: =IF(C10="","",C10) | F10: Descendente | G10: =IF(C10="","SIN DATO","COMPARAR") -> SIN DATO
A11: 6 | B11: Tasa de conversión de la primera visita | E11: =IF(OR(C11="",D11="",D11=0),"",C11/D11) | F11: Línea base y mejora | G11: =IF(C11="","SIN DATO",IF(E11>=Definiciones!$G$10,"VERDE",IF(E11>=Definiciones!$H$10,"ÁMBAR","ROJO"))) -> SIN DATO
A12: 7 | B12: Pacientes en mantenimiento activo | E12: =IF(OR(C12="",D12="",D12=0),"",C12/D12) | F12: Creciente | G12: =IF(C12="","SIN DATO",IF(E12>=Definiciones!$G$11,"VERDE",IF(E12>=Definiciones!$H$11,"ÁMBAR","ROJO"))) -> SIN DATO | H12: Provisional
A13: 8 | B13: Captación por recomendación | E13: =IF(OR(C13="",D13="",D13=0),"",C13/D13) | F13: Creciente | G13: =IF(C13="","SIN DATO",IF(E13>=Definiciones!$G$12,"VERDE",IF(E13>=Definiciones!$H$12,"ÁMBAR","ROJO"))) -> SIN DATO
A14: 9 | B14: Ofrecimiento del programa de cuidado | E14: =IF(OR(C14="",D14="",D14=0),"",C14/D14) | F14: 90 % | G14: =IF(C14="","SIN DATO",IF(E14>=Definiciones!$G$13,"VERDE",IF(E14>=Definiciones!$H$13,"ÁMBAR","ROJO"))) -> SIN DATO
A15: 10 | B15: Auditorías ejecutadas en fecha | E15: =IF(OR(C15="",D15="",D15=0),"",C15/D15) | F15: 100 % | G15: =IF(C15="","SIN DATO",IF(E15>=Definiciones!$G$14,"VERDE",IF(E15>=Definiciones!$H$14,"ÁMBAR","ROJO"))) -> SIN DATO
B17: El indicador 5 se compara con el mes anterior: la casilla dice COMPARAR porque el sentido «descendente» exige mirar la serie, no un umbral fijo.
B18: Un indicador en SIN DATO cuenta como rojo en la revisión de Junta.

Sheet 06 Junio
A1: Captura mensual · Junio de 2026
A2: Rellénense únicamente las casillas amarillas. El resultado y el semáforo se calculan solos.
A4: # | B4: Indicador | C4: Numerador | D4: Denominador | E4: Resultado | F4: Umbral | G4: Estado | H4: Estado del dato | I4: Notas
A6: 1 | B6: Verificaciones regulatorias cerradas | D6: 11 | E6: =IF(OR(C6="",D6="",D6=0),"",C6/D6) | F6: 11 de 11 | G6: =IF(C6="","SIN DATO",IF(E6>=Definiciones!$G$5,"VERDE",IF(E6>=Definiciones!$H$5,"ÁMBAR","ROJO"))) -> SIN DATO
A7: 2 | B7: Bajas voluntarias del equipo | E7: =IF(OR(C7="",D7="",D7=0),"",C7/D7) | F7: 0 | G7: =IF(C7="","SIN DATO",IF(E7<=Definiciones!$G$6,"VERDE",IF(E7<=Definiciones!$H$6,"ÁMBAR","ROJO"))) -> SIN DATO
A8: 3 | B8: Reclamaciones de pacientes heredados | D8: — | E8: =IF(C8="","",C8) | F8: 0 | G8: =IF(C8="","SIN DATO",IF(E8<=Definiciones!$G$7,"VERDE",IF(E8<=Definiciones!$H$7,"ÁMBAR","ROJO"))) -> SIN DATO
A9: 4 | B9: Documentación digitalizada el mismo día | E9: =IF(OR(C9="",D9="",D9=0),"",C9/D9) | F9: 100 % | G9: =IF(C9="","SIN DATO",IF(E9>=Definiciones!$G$8,"VERDE",IF(E9>=Definiciones!$H$8,"ÁMBAR","ROJO"))) -> SIN DATO
A10: 5 | B10: Producto pendiente | D10: — | E10: =IF(C10="","",C10) | F10: Descendente | G10: =IF(C10="","SIN DATO","COMPARAR") -> SIN DATO
A11: 6 | B11: Tasa de conversión de la primera visita | E11: =IF(OR(C11="",D11="",D11=0),"",C11/D11) | F11: Línea base y mejora | G11: =IF(C11="","SIN DATO",IF(E11>=Definiciones!$G$10,"VERDE",IF(E11>=Definiciones!$H$10,"ÁMBAR","ROJO"))) -> SIN DATO
A12: 7 | B12: Pacientes en mantenimiento activo | E12: =IF(OR(C12="",D12="",D12=0),"",C12/D12) | F12: Creciente | G12: =IF(C12="","SIN DATO",IF(E12>=Definiciones!$G$11,"VERDE",IF(E12>=Definiciones!$H$11,"ÁMBAR","ROJO"))) -> SIN DATO | H12: Provisional
A13: 8 | B13: Captación por recomendación | E13: =IF(OR(C13="",D13="",D13=0),"",C13/D13) | F13: Creciente | G13: =IF(C13="","SIN DATO",IF(E13>=Definiciones!$G$12,"VERDE",IF(E13>=Definiciones!$H$12,"ÁMBAR","ROJO"))) -> SIN DATO
A14: 9 | B14: Ofrecimiento del programa de cuidado | E14: =IF(OR(C14="",D14="",D14=0),"",C14/D14) | F14: 90 % | G14: =IF(C14="","SIN DATO",IF(E14>=Definiciones!$G$13,"VERDE",IF(E14>=Definiciones!$H$13,"ÁMBAR","ROJO"))) -> SIN DATO
A15: 10 | B15: Auditorías ejecutadas en fecha | E15: =IF(OR(C15="",D15="",D15=0),"",C15/D15) | F15: 100 % | G15: =IF(C15="","SIN DATO",IF(E15>=Definiciones!$G$14,"VERDE",IF(E15>=Definiciones!$H$14,"ÁMBAR","ROJO"))) -> SIN DATO
B17: El indicador 5 se compara con el mes anterior: la casilla dice COMPARAR porque el sentido «descendente» exige mirar la serie, no un umbral fijo.
B18: Un indicador en SIN DATO cuenta como rojo en la revisión de Junta.

Sheet 07 Julio
A1: Captura mensual · Julio de 2026
A2: Rellénense únicamente las casillas amarillas. El resultado y el semáforo se calculan solos.
A4: # | B4: Indicador | C4: Numerador | D4: Denominador | E4: Resultado | F4: Umbral | G4: Estado | H4: Estado del dato | I4: Notas
A6: 1 | B6: Verificaciones regulatorias cerradas | D6: 11 | E6: =IF(OR(C6="",D6="",D6=0),"",C6/D6) | F6: 11 de 11 | G6: =IF(C6="","SIN DATO",IF(E6>=Definiciones!$G$5,"VERDE",IF(E6>=Definiciones!$H$5,"ÁMBAR","ROJO"))) -> SIN DATO
A7: 2 | B7: Bajas voluntarias del equipo | E7: =IF(OR(C7="",D7="",D7=0),"",C7/D7) | F7: 0 | G7: =IF(C7="","SIN DATO",IF(E7<=Definiciones!$G$6,"VERDE",IF(E7<=Definiciones!$H$6,"ÁMBAR","ROJO"))) -> SIN DATO
A8: 3 | B8: Reclamaciones de pacientes heredados | D8: — | E8: =IF(C8="","",C8) | F8: 0 | G8: =IF(C8="","SIN DATO",IF(E8<=Definiciones!$G$7,"VERDE",IF(E8<=Definiciones!$H$7,"ÁMBAR","ROJO"))) -> SIN DATO
A9: 4 | B9: Documentación digitalizada el mismo día | E9: =IF(OR(C9="",D9="",D9=0),"",C9/D9) | F9: 100 % | G9: =IF(C9="","SIN DATO",IF(E9>=Definiciones!$G$8,"VERDE",IF(E9>=Definiciones!$H$8,"ÁMBAR","ROJO"))) -> SIN DATO
A10: 5 | B10: Producto pendiente | D10: — | E10: =IF(C10="","",C10) | F10: Descendente | G10: =IF(C10="","SIN DATO","COMPARAR") -> SIN DATO
A11: 6 | B11: Tasa de conversión de la primera visita | E11: =IF(OR(C11="",D11="",D11=0),"",C11/D11) | F11: Línea base y mejora | G11: =IF(C11="","SIN DATO",IF(E11>=Definiciones!$G$10,"VERDE",IF(E11>=Definiciones!$H$10,"ÁMBAR","ROJO"))) -> SIN DATO
A12: 7 | B12: Pacientes en mantenimiento activo | E12: =IF(OR(C12="",D12="",D12=0),"",C12/D12) | F12: Creciente | G12: =IF(C12="","SIN DATO",IF(E12>=Definiciones!$G$11,"VERDE",IF(E12>=Definiciones!$H$11,"ÁMBAR","ROJO"))) -> SIN DATO | H12: Provisional
A13: 8 | B13: Captación por recomendación | E13: =IF(OR(C13="",D13="",D13=0),"",C13/D13) | F13: Creciente | G13: =IF(C13="","SIN DATO",IF(E13>=Definiciones!$G$12,"VERDE",IF(E13>=Definiciones!$H$12,"ÁMBAR","ROJO"))) -> SIN DATO
A14: 9 | B14: Ofrecimiento del programa de cuidado | E14: =IF(OR(C14="",D14="",D14=0),"",C14/D14) | F14: 90 % | G14: =IF(C14="","SIN DATO",IF(E14>=Definiciones!$G$13,"VERDE",IF(E14>=Definiciones!$H$13,"ÁMBAR","ROJO"))) -> SIN DATO
A15: 10 | B15: Auditorías ejecutadas en fecha | E15: =IF(OR(C15="",D15="",D15=0),"",C15/D15) | F15: 100 % | G15: =IF(C15="","SIN DATO",IF(E15>=Definiciones!$G$14,"VERDE",IF(E15>=Definiciones!$H$14,"ÁMBAR","ROJO"))) -> SIN DATO
B17: El indicador 5 se compara con el mes anterior: la casilla dice COMPARAR porque el sentido «descendente» exige mirar la serie, no un umbral fijo.
B18: Un indicador en SIN DATO cuenta como rojo en la revisión de Junta.

Sheet 08 Agosto
A1: Captura mensual · Agosto de 2026
A2: Rellénense únicamente las casillas amarillas. El resultado y el semáforo se calculan solos.
A4: # | B4: Indicador | C4: Numerador | D4: Denominador | E4: Resultado | F4: Umbral | G4: Estado | H4: Estado del dato | I4: Notas
A6: 1 | B6: Verificaciones regulatorias cerradas | D6: 11 | E6: =IF(OR(C6="",D6="",D6=0),"",C6/D6) | F6: 11 de 11 | G6: =IF(C6="","SIN DATO",IF(E6>=Definiciones!$G$5,"VERDE",IF(E6>=Definiciones!$H$5,"ÁMBAR","ROJO"))) -> SIN DATO
A7: 2 | B7: Bajas voluntarias del equipo | E7: =IF(OR(C7="",D7="",D7=0),"",C7/D7) | F7: 0 | G7: =IF(C7="","SIN DATO",IF(E7<=Definiciones!$G$6,"VERDE",IF(E7<=Definiciones!$H$6,"ÁMBAR","ROJO"))) -> SIN DATO
A8: 3 | B8: Reclamaciones de pacientes heredados | D8: — | E8: =IF(C8="","",C8) | F8: 0 | G8: =IF(C8="","SIN DATO",IF(E8<=Definiciones!$G$7,"VERDE",IF(E8<=Definiciones!$H$7,"ÁMBAR","ROJO"))) -> SIN DATO
A9: 4 | B9: Documentación digitalizada el mismo día | E9: =IF(OR(C9="",D9="",D9=0),"",C9/D9) | F9: 100 % | G9: =IF(C9="","SIN DATO",IF(E9>=Definiciones!$G$8,"VERDE",IF(E9>=Definiciones!$H$8,"ÁMBAR","ROJO"))) -> SIN DATO
A10: 5 | B10: Producto pendiente | D10: — | E10: =IF(C10="","",C10) | F10: Descendente | G10: =IF(C10="","SIN DATO","COMPARAR") -> SIN DATO
A11: 6 | B11: Tasa de conversión de la primera visita | E11: =IF(OR(C11="",D11="",D11=0),"",C11/D11) | F11: Línea base y mejora | G11: =IF(C11="","SIN DATO",IF(E11>=Definiciones!$G$10,"VERDE",IF(E11>=Definiciones!$H$10,"ÁMBAR","ROJO"))) -> SIN DATO
A12: 7 | B12: Pacientes en mantenimiento activo | E12: =IF(OR(C12="",D12="",D12=0),"",C12/D12) | F12: Creciente | G12: =IF(C12="","SIN DATO",IF(E12>=Definiciones!$G$11,"VERDE",IF(E12>=Definiciones!$H$11,"ÁMBAR","ROJO"))) -> SIN DATO | H12: Provisional
A13: 8 | B13: Captación por recomendación | E13: =IF(OR(C13="",D13="",D13=0),"",C13/D13) | F13: Creciente | G13: =IF(C13="","SIN DATO",IF(E13>=Definiciones!$G$12,"VERDE",IF(E13>=Definiciones!$H$12,"ÁMBAR","ROJO"))) -> SIN DATO
A14: 9 | B14: Ofrecimiento del programa de cuidado | E14: =IF(OR(C14="",D14="",D14=0),"",C14/D14) | F14: 90 % | G14: =IF(C14="","SIN DATO",IF(E14>=Definiciones!$G$13,"VERDE",IF(E14>=Definiciones!$H$13,"ÁMBAR","ROJO"))) -> SIN DATO
A15: 10 | B15: Auditorías ejecutadas en fecha | E15: =IF(OR(C15="",D15="",D15=0),"",C15/D15) | F15: 100 % | G15: =IF(C15="","SIN DATO",IF(E15>=Definiciones!$G$14,"VERDE",IF(E15>=Definiciones!$H$14,"ÁMBAR","ROJO"))) -> SIN DATO
B17: El indicador 5 se compara con el mes anterior: la casilla dice COMPARAR porque el sentido «descendente» exige mirar la serie, no un umbral fijo.
B18: Un indicador en SIN DATO cuenta como rojo en la revisión de Junta.

Sheet 09 Septiembre
A1: Captura mensual · Septiembre de 2026
A2: Rellénense únicamente las casillas amarillas. El resultado y el semáforo se calculan solos.
A4: # | B4: Indicador | C4: Numerador | D4: Denominador | E4: Resultado | F4: Umbral | G4: Estado | H4: Estado del dato | I4: Notas
A6: 1 | B6: Verificaciones regulatorias cerradas | D6: 11 | E6: =IF(OR(C6="",D6="",D6=0),"",C6/D6) | F6: 11 de 11 | G6: =IF(C6="","SIN DATO",IF(E6>=Definiciones!$G$5,"VERDE",IF(E6>=Definiciones!$H$5,"ÁMBAR","ROJO"))) -> SIN DATO
A7: 2 | B7: Bajas voluntarias del equipo | E7: =IF(OR(C7="",D7="",D7=0),"",C7/D7) | F7: 0 | G7: =IF(C7="","SIN DATO",IF(E7<=Definiciones!$G$6,"VERDE",IF(E7<=Definiciones!$H$6,"ÁMBAR","ROJO"))) -> SIN DATO
A8: 3 | B8: Reclamaciones de pacientes heredados | D8: — | E8: =IF(C8="","",C8) | F8: 0 | G8: =IF(C8="","SIN DATO",IF(E8<=Definiciones!$G$7,"VERDE",IF(E8<=Definiciones!$H$7,"ÁMBAR","ROJO"))) -> SIN DATO
A9: 4 | B9: Documentación digitalizada el mismo día | E9: =IF(OR(C9="",D9="",D9=0),"",C9/D9) | F9: 100 % | G9: =IF(C9="","SIN DATO",IF(E9>=Definiciones!$G$8,"VERDE",IF(E9>=Definiciones!$H$8,"ÁMBAR","ROJO"))) -> SIN DATO
A10: 5 | B10: Producto pendiente | D10: — | E10: =IF(C10="","",C10) | F10: Descendente | G10: =IF(C10="","SIN DATO","COMPARAR") -> SIN DATO
A11: 6 | B11: Tasa de conversión de la primera visita | E11: =IF(OR(C11="",D11="",D11=0),"",C11/D11) | F11: Línea base y mejora | G11: =IF(C11="","SIN DATO",IF(E11>=Definiciones!$G$10,"VERDE",IF(E11>=Definiciones!$H$10,"ÁMBAR","ROJO"))) -> SIN DATO
A12: 7 | B12: Pacientes en mantenimiento activo | E12: =IF(OR(C12="",D12="",D12=0),"",C12/D12) | F12: Creciente | G12: =IF(C12="","SIN DATO",IF(E12>=Definiciones!$G$11,"VERDE",IF(E12>=Definiciones!$H$11,"ÁMBAR","ROJO"))) -> SIN DATO | H12: Provisional
A13: 8 | B13: Captación por recomendación | E13: =IF(OR(C13="",D13="",D13=0),"",C13/D13) | F13: Creciente | G13: =IF(C13="","SIN DATO",IF(E13>=Definiciones!$G$12,"VERDE",IF(E13>=Definiciones!$H$12,"ÁMBAR","ROJO"))) -> SIN DATO
A14: 9 | B14: Ofrecimiento del programa de cuidado | E14: =IF(OR(C14="",D14="",D14=0),"",C14/D14) | F14: 90 % | G14: =IF(C14="","SIN DATO",IF(E14>=Definiciones!$G$13,"VERDE",IF(E14>=Definiciones!$H$13,"ÁMBAR","ROJO"))) -> SIN DATO
A15: 10 | B15: Auditorías ejecutadas en fecha | E15: =IF(OR(C15="",D15="",D15=0),"",C15/D15) | F15: 100 % | G15: =IF(C15="","SIN DATO",IF(E15>=Definiciones!$G$14,"VERDE",IF(E15>=Definiciones!$H$14,"ÁMBAR","ROJO"))) -> SIN DATO
B17: El indicador 5 se compara con el mes anterior: la casilla dice COMPARAR porque el sentido «descendente» exige mirar la serie, no un umbral fijo.
B18: Un indicador en SIN DATO cuenta como rojo en la revisión de Junta.

Sheet 10 Octubre
A1: Captura mensual · Octubre de 2026
A2: Rellénense únicamente las casillas amarillas. El resultado y el semáforo se calculan solos.
A4: # | B4: Indicador | C4: Numerador | D4: Denominador | E4: Resultado | F4: Umbral | G4: Estado | H4: Estado del dato | I4: Notas
A6: 1 | B6: Verificaciones regulatorias cerradas | D6: 11 | E6: =IF(OR(C6="",D6="",D6=0),"",C6/D6) | F6: 11 de 11 | G6: =IF(C6="","SIN DATO",IF(E6>=Definiciones!$G$5,"VERDE",IF(E6>=Definiciones!$H$5,"ÁMBAR","ROJO"))) -> SIN DATO
A7: 2 | B7: Bajas voluntarias del equipo | E7: =IF(OR(C7="",D7="",D7=0),"",C7/D7) | F7: 0 | G7: =IF(C7="","SIN DATO",IF(E7<=Definiciones!$G$6,"VERDE",IF(E7<=Definiciones!$H$6,"ÁMBAR","ROJO"))) -> SIN DATO
A8: 3 | B8: Reclamaciones de pacientes heredados | D8: — | E8: =IF(C8="","",C8) | F8: 0 | G8: =IF(C8="","SIN DATO",IF(E8<=Definiciones!$G$7,"VERDE",IF(E8<=Definiciones!$H$7,"ÁMBAR","ROJO"))) -> SIN DATO
A9: 4 | B9: Documentación digitalizada el mismo día | E9: =IF(OR(C9="",D9="",D9=0),"",C9/D9) | F9: 100 % | G9: =IF(C9="","SIN DATO",IF(E9>=Definiciones!$G$8,"VERDE",IF(E9>=Definiciones!$H$8,"ÁMBAR","ROJO"))) -> SIN DATO
A10: 5 | B10: Producto pendiente | D10: — | E10: =IF(C10="","",C10) | F10: Descendente | G10: =IF(C10="","SIN DATO","COMPARAR") -> SIN DATO
A11: 6 | B11: Tasa de conversión de la primera visita | E11: =IF(OR(C11="",D11="",D11=0),"",C11/D11) | F11: Línea base y mejora | G11: =IF(C11="","SIN DATO",IF(E11>=Definiciones!$G$10,"VERDE",IF(E11>=Definiciones!$H$10,"ÁMBAR","ROJO"))) -> SIN DATO
A12: 7 | B12: Pacientes en mantenimiento activo | E12: =IF(OR(C12="",D12="",D12=0),"",C12/D12) | F12: Creciente | G12: =IF(C12="","SIN DATO",IF(E12>=Definiciones!$G$11,"VERDE",IF(E12>=Definiciones!$H$11,"ÁMBAR","ROJO"))) -> SIN DATO | H12: Provisional
A13: 8 | B13: Captación por recomendación | E13: =IF(OR(C13="",D13="",D13=0),"",C13/D13) | F13: Creciente | G13: =IF(C13="","SIN DATO",IF(E13>=Definiciones!$G$12,"VERDE",IF(E13>=Definiciones!$H$12,"ÁMBAR","ROJO"))) -> SIN DATO
A14: 9 | B14: Ofrecimiento del programa de cuidado | E14: =IF(OR(C14="",D14="",D14=0),"",C14/D14) | F14: 90 % | G14: =IF(C14="","SIN DATO",IF(E14>=Definiciones!$G$13,"VERDE",IF(E14>=Definiciones!$H$13,"ÁMBAR","ROJO"))) -> SIN DATO
A15: 10 | B15: Auditorías ejecutadas en fecha | E15: =IF(OR(C15="",D15="",D15=0),"",C15/D15) | F15: 100 % | G15: =IF(C15="","SIN DATO",IF(E15>=Definiciones!$G$14,"VERDE",IF(E15>=Definiciones!$H$14,"ÁMBAR","ROJO"))) -> SIN DATO
B17: El indicador 5 se compara con el mes anterior: la casilla dice COMPARAR porque el sentido «descendente» exige mirar la serie, no un umbral fijo.
B18: Un indicador en SIN DATO cuenta como rojo en la revisión de Junta.

Sheet 11 Noviembre
A1: Captura mensual · Noviembre de 2026
A2: Rellénense únicamente las casillas amarillas. El resultado y el semáforo se calculan solos.
A4: # | B4: Indicador | C4: Numerador | D4: Denominador | E4: Resultado | F4: Umbral | G4: Estado | H4: Estado del dato | I4: Notas
A6: 1 | B6: Verificaciones regulatorias cerradas | D6: 11 | E6: =IF(OR(C6="",D6="",D6=0),"",C6/D6) | F6: 11 de 11 | G6: =IF(C6="","SIN DATO",IF(E6>=Definiciones!$G$5,"VERDE",IF(E6>=Definiciones!$H$5,"ÁMBAR","ROJO"))) -> SIN DATO
A7: 2 | B7: Bajas voluntarias del equipo | E7: =IF(OR(C7="",D7="",D7=0),"",C7/D7) | F7: 0 | G7: =IF(C7="","SIN DATO",IF(E7<=Definiciones!$G$6,"VERDE",IF(E7<=Definiciones!$H$6,"ÁMBAR","ROJO"))) -> SIN DATO
A8: 3 | B8: Reclamaciones de pacientes heredados | D8: — | E8: =IF(C8="","",C8) | F8: 0 | G8: =IF(C8="","SIN DATO",IF(E8<=Definiciones!$G$7,"VERDE",IF(E8<=Definiciones!$H$7,"ÁMBAR","ROJO"))) -> SIN DATO
A9: 4 | B9: Documentación digitalizada el mismo día | E9: =IF(OR(C9="",D9="",D9=0),"",C9/D9) | F9: 100 % | G9: =IF(C9="","SIN DATO",IF(E9>=Definiciones!$G$8,"VERDE",IF(E9>=Definiciones!$H$8,"ÁMBAR","ROJO"))) -> SIN DATO
A10: 5 | B10: Producto pendiente | D10: — | E10: =IF(C10="","",C10) | F10: Descendente | G10: =IF(C10="","SIN DATO","COMPARAR") -> SIN DATO
A11: 6 | B11: Tasa de conversión de la primera visita | E11: =IF(OR(C11="",D11="",D11=0),"",C11/D11) | F11: Línea base y mejora | G11: =IF(C11="","SIN DATO",IF(E11>=Definiciones!$G$10,"VERDE",IF(E11>=Definiciones!$H$10,"ÁMBAR","ROJO"))) -> SIN DATO
A12: 7 | B12: Pacientes en mantenimiento activo | E12: =IF(OR(C12="",D12="",D12=0),"",C12/D12) | F12: Creciente | G12: =IF(C12="","SIN DATO",IF(E12>=Definiciones!$G$11,"VERDE",IF(E12>=Definiciones!$H$11,"ÁMBAR","ROJO"))) -> SIN DATO | H12: Provisional
A13: 8 | B13: Captación por recomendación | E13: =IF(OR(C13="",D13="",D13=0),"",C13/D13) | F13: Creciente | G13: =IF(C13="","SIN DATO",IF(E13>=Definiciones!$G$12,"VERDE",IF(E13>=Definiciones!$H$12,"ÁMBAR","ROJO"))) -> SIN DATO
A14: 9 | B14: Ofrecimiento del programa de cuidado | E14: =IF(OR(C14="",D14="",D14=0),"",C14/D14) | F14: 90 % | G14: =IF(C14="","SIN DATO",IF(E14>=Definiciones!$G$13,"VERDE",IF(E14>=Definiciones!$H$13,"ÁMBAR","ROJO"))) -> SIN DATO
A15: 10 | B15: Auditorías ejecutadas en fecha | E15: =IF(OR(C15="",D15="",D15=0),"",C15/D15) | F15: 100 % | G15: =IF(C15="","SIN DATO",IF(E15>=Definiciones!$G$14,"VERDE",IF(E15>=Definiciones!$H$14,"ÁMBAR","ROJO"))) -> SIN DATO
B17: El indicador 5 se compara con el mes anterior: la casilla dice COMPARAR porque el sentido «descendente» exige mirar la serie, no un umbral fijo.
B18: Un indicador en SIN DATO cuenta como rojo en la revisión de Junta.

Sheet 12 Diciembre
A1: Captura mensual · Diciembre de 2026
A2: Rellénense únicamente las casillas amarillas. El resultado y el semáforo se calculan solos.
A4: # | B4: Indicador | C4: Numerador | D4: Denominador | E4: Resultado | F4: Umbral | G4: Estado | H4: Estado del dato | I4: Notas
A6: 1 | B6: Verificaciones regulatorias cerradas | D6: 11 | E6: =IF(OR(C6="",D6="",D6=0),"",C6/D6) | F6: 11 de 11 | G6: =IF(C6="","SIN DATO",IF(E6>=Definiciones!$G$5,"VERDE",IF(E6>=Definiciones!$H$5,"ÁMBAR","ROJO"))) -> SIN DATO
A7: 2 | B7: Bajas voluntarias del equipo | E7: =IF(OR(C7="",D7="",D7=0),"",C7/D7) | F7: 0 | G7: =IF(C7="","SIN DATO",IF(E7<=Definiciones!$G$6,"VERDE",IF(E7<=Definiciones!$H$6,"ÁMBAR","ROJO"))) -> SIN DATO
A8: 3 | B8: Reclamaciones de pacientes heredados | D8: — | E8: =IF(C8="","",C8) | F8: 0 | G8: =IF(C8="","SIN DATO",IF(E8<=Definiciones!$G$7,"VERDE",IF(E8<=Definiciones!$H$7,"ÁMBAR","ROJO"))) -> SIN DATO
A9: 4 | B9: Documentación digitalizada el mismo día | E9: =IF(OR(C9="",D9="",D9=0),"",C9/D9) | F9: 100 % | G9: =IF(C9="","SIN DATO",IF(E9>=Definiciones!$G$8,"VERDE",IF(E9>=Definiciones!$H$8,"ÁMBAR","ROJO"))) -> SIN DATO
A10: 5 | B10: Producto pendiente | D10: — | E10: =IF(C10="","",C10) | F10: Descendente | G10: =IF(C10="","SIN DATO","COMPARAR") -> SIN DATO
A11: 6 | B11: Tasa de conversión de la primera visita | E11: =IF(OR(C11="",D11="",D11=0),"",C11/D11) | F11: Línea base y mejora | G11: =IF(C11="","SIN DATO",IF(E11>=Definiciones!$G$10,"VERDE",IF(E11>=Definiciones!$H$10,"ÁMBAR","ROJO"))) -> SIN DATO
A12: 7 | B12: Pacientes en mantenimiento activo | E12: =IF(OR(C12="",D12="",D12=0),"",C12/D12) | F12: Creciente | G12: =IF(C12="","SIN DATO",IF(E12>=Definiciones!$G$11,"VERDE",IF(E12>=Definiciones!$H$11,"ÁMBAR","ROJO"))) -> SIN DATO | H12: Provisional
A13: 8 | B13: Captación por recomendación | E13: =IF(OR(C13="",D13="",D13=0),"",C13/D13) | F13: Creciente | G13: =IF(C13="","SIN DATO",IF(E13>=Definiciones!$G$12,"VERDE",IF(E13>=Definiciones!$H$12,"ÁMBAR","ROJO"))) -> SIN DATO
A14: 9 | B14: Ofrecimiento del programa de cuidado | E14: =IF(OR(C14="",D14="",D14=0),"",C14/D14) | F14: 90 % | G14: =IF(C14="","SIN DATO",IF(E14>=Definiciones!$G$13,"VERDE",IF(E14>=Definiciones!$H$13,"ÁMBAR","ROJO"))) -> SIN DATO
A15: 10 | B15: Auditorías ejecutadas en fecha | E15: =IF(OR(C15="",D15="",D15=0),"",C15/D15) | F15: 100 % | G15: =IF(C15="","SIN DATO",IF(E15>=Definiciones!$G$14,"VERDE",IF(E15>=Definiciones!$H$14,"ÁMBAR","ROJO"))) -> SIN DATO
B17: El indicador 5 se compara con el mes anterior: la casilla dice COMPARAR porque el sentido «descendente» exige mirar la serie, no un umbral fijo.
B18: Un indicador en SIN DATO cuenta como rojo en la revisión de Junta.

Sheet Resumen anual
A1: Resumen anual · los doce meses en una rejilla
A2: Todo se recoge de las hojas mensuales. «Meses con dato» es la medida honesta de cuánto sabemos realmente: la Junta debe exigir que llegue a doce.
A4: # | B4: Indicador | C4: Ene | D4: Feb | E4: Mar | F4: Abr | G4: May | H4: Jun | I4: Jul | J4: Ago | K4: Sep | L4: Oct | M4: Nov | N4: Dic | O4: Meses con dato | P4: Primero | Q4: Último | R4: Tendencia
A5: 1 | B5: Verificaciones regulatorias cerradas | C5: =IF('01 Enero'!E6="","",'01 Enero'!E6) | D5: =IF('02 Febrero'!E6="","",'02 Febrero'!E6) | E5: =IF('03 Marzo'!E6="","",'03 Marzo'!E6) | F5: =IF('04 Abril'!E6="","",'04 Abril'!E6) | G5: =IF('05 Mayo'!E6="","",'05 Mayo'!E6) | H5: =IF('06 Junio'!E6="","",'06 Junio'!E6) | I5: =IF('07 Julio'!E6="","",'07 Julio'!E6) | J5: =IF('08 Agosto'!E6="","",'08 Agosto'!E6) | K5: =IF('09 Septiembre'!E6="","",'09 Septiembre'!E6) | L5: =IF('10 Octubre'!E6="","",'10 Octubre'!E6) | M5: =IF('11 Noviembre'!E6="","",'11 Noviembre'!E6) | N5: =IF('12 Diciembre'!E6="","",'12 Diciembre'!E6) | O5: =COUNT(C5:N5) -> 0 | P5: =IFERROR(INDEX(C5:N5,MATCH(TRUE(),INDEX(C5:N5<>"",0),0)),"") | Q5: =IFERROR(LOOKUP(9.99E+307,C5:N5),"") | R5: =IF(O5<2,"—",IF(Q5=P5,"Estable",IF(Q5>P5,"Mejora","Empeora"))) -> —
A6: 2 | B6: Bajas voluntarias del equipo | C6: =IF('01 Enero'!E7="","",'01 Enero'!E7) | D6: =IF('02 Febrero'!E7="","",'02 Febrero'!E7) | E6: =IF('03 Marzo'!E7="","",'03 Marzo'!E7) | F6: =IF('04 Abril'!E7="","",'04 Abril'!E7) | G6: =IF('05 Mayo'!E7="","",'05 Mayo'!E7) | H6: =IF('06 Junio'!E7="","",'06 Junio'!E7) | I6: =IF('07 Julio'!E7="","",'07 Julio'!E7) | J6: =IF('08 Agosto'!E7="","",'08 Agosto'!E7) | K6: =IF('09 Septiembre'!E7="","",'09 Septiembre'!E7) | L6: =IF('10 Octubre'!E7="","",'10 Octubre'!E7) | M6: =IF('11 Noviembre'!E7="","",'11 Noviembre'!E7) | N6: =IF('12 Diciembre'!E7="","",'12 Diciembre'!E7) | O6: =COUNT(C6:N6) -> 0 | P6: =IFERROR(INDEX(C6:N6,MATCH(TRUE(),INDEX(C6:N6<>"",0),0)),"") | Q6: =IFERROR(LOOKUP(9.99E+307,C6:N6),"") | R6: =IF(O6<2,"—",IF(Q6=P6,"Estable",IF(Q6<P6,"Mejora","Empeora"))) -> —
A7: 3 | B7: Reclamaciones de pacientes heredados | C7: =IF('01 Enero'!E8="","",'01 Enero'!E8) | D7: =IF('02 Febrero'!E8="","",'02 Febrero'!E8) | E7: =IF('03 Marzo'!E8="","",'03 Marzo'!E8) | F7: =IF('04 Abril'!E8="","",'04 Abril'!E8) | G7: =IF('05 Mayo'!E8="","",'05 Mayo'!E8) | H7: =IF('06 Junio'!E8="","",'06 Junio'!E8) | I7: =IF('07 Julio'!E8="","",'07 Julio'!E8) | J7: =IF('08 Agosto'!E8="","",'08 Agosto'!E8) | K7: =IF('09 Septiembre'!E8="","",'09 Septiembre'!E8) | L7: =IF('10 Octubre'!E8="","",'10 Octubre'!E8) | M7: =IF('11 Noviembre'!E8="","",'11 Noviembre'!E8) | N7: =IF('12 Diciembre'!E8="","",'12 Diciembre'!E8) | O7: =COUNT(C7:N7) -> 0 | P7: =IFERROR(INDEX(C7:N7,MATCH(TRUE(),INDEX(C7:N7<>"",0),0)),"") | Q7: =IFERROR(LOOKUP(9.99E+307,C7:N7),"") | R7: =IF(O7<2,"—",IF(Q7=P7,"Estable",IF(Q7<P7,"Mejora","Empeora"))) -> —
A8: 4 | B8: Documentación digitalizada el mismo día | C8: =IF('01 Enero'!E9="","",'01 Enero'!E9) | D8: =IF('02 Febrero'!E9="","",'02 Febrero'!E9) | E8: =IF('03 Marzo'!E9="","",'03 Marzo'!E9) | F8: =IF('04 Abril'!E9="","",'04 Abril'!E9) | G8: =IF('05 Mayo'!E9="","",'05 Mayo'!E9) | H8: =IF('06 Junio'!E9="","",'06 Junio'!E9) | I8: =IF('07 Julio'!E9="","",'07 Julio'!E9) | J8: =IF('08 Agosto'!E9="","",'08 Agosto'!E9) | K8: =IF('09 Septiembre'!E9="","",'09 Septiembre'!E9) | L8: =IF('10 Octubre'!E9="","",'10 Octubre'!E9) | M8: =IF('11 Noviembre'!E9="","",'11 Noviembre'!E9) | N8: =IF('12 Diciembre'!E9="","",'12 Diciembre'!E9) | O8: =COUNT(C8:N8) -> 0 | P8: =IFERROR(INDEX(C8:N8,MATCH(TRUE(),INDEX(C8:N8<>"",0),0)),"") | Q8: =IFERROR(LOOKUP(9.99E+307,C8:N8),"") | R8: =IF(O8<2,"—",IF(Q8=P8,"Estable",IF(Q8>P8,"Mejora","Empeora"))) -> —
A9: 5 | B9: Producto pendiente | C9: =IF('01 Enero'!E10="","",'01 Enero'!E10) | D9: =IF('02 Febrero'!E10="","",'02 Febrero'!E10) | E9: =IF('03 Marzo'!E10="","",'03 Marzo'!E10) | F9: =IF('04 Abril'!E10="","",'04 Abril'!E10) | G9: =IF('05 Mayo'!E10="","",'05 Mayo'!E10) | H9: =IF('06 Junio'!E10="","",'06 Junio'!E10) | I9: =IF('07 Julio'!E10="","",'07 Julio'!E10) | J9: =IF('08 Agosto'!E10="","",'08 Agosto'!E10) | K9: =IF('09 Septiembre'!E10="","",'09 Septiembre'!E10) | L9: =IF('10 Octubre'!E10="","",'10 Octubre'!E10) | M9: =IF('11 Noviembre'!E10="","",'11 Noviembre'!E10) | N9: =IF('12 Diciembre'!E10="","",'12 Diciembre'!E10) | O9: =COUNT(C9:N9) -> 0 | P9: =IFERROR(INDEX(C9:N9,MATCH(TRUE(),INDEX(C9:N9<>"",0),0)),"") | Q9: =IFERROR(LOOKUP(9.99E+307,C9:N9),"") | R9: =IF(O9<2,"—",IF(Q9=P9,"Estable",IF(Q9<P9,"Mejora","Empeora"))) -> —
A10: 6 | B10: Tasa de conversión de la primera visita | C10: =IF('01 Enero'!E11="","",'01 Enero'!E11) | D10: =IF('02 Febrero'!E11="","",'02 Febrero'!E11) | E10: =IF('03 Marzo'!E11="","",'03 Marzo'!E11) | F10: =IF('04 Abril'!E11="","",'04 Abril'!E11) | G10: =IF('05 Mayo'!E11="","",'05 Mayo'!E11) | H10: =IF('06 Junio'!E11="","",'06 Junio'!E11) | I10: =IF('07 Julio'!E11="","",'07 Julio'!E11) | J10: =IF('08 Agosto'!E11="","",'08 Agosto'!E11) | K10: =IF('09 Septiembre'!E11="","",'09 Septiembre'!E11) | L10: =IF('10 Octubre'!E11="","",'10 Octubre'!E11) | M10: =IF('11 Noviembre'!E11="","",'11 Noviembre'!E11) | N10: =IF('12 Diciembre'!E11="","",'12 Diciembre'!E11) | O10: =COUNT(C10:N10) -> 0 | P10: =IFERROR(INDEX(C10:N10,MATCH(TRUE(),INDEX(C10:N10<>"",0),0)),"") | Q10: =IFERROR(LOOKUP(9.99E+307,C10:N10),"") | R10: =IF(O10<2,"—",IF(Q10=P10,"Estable",IF(Q10>P10,"Mejora","Empeora"))) -> —
A11: 7 | B11: Pacientes en mantenimiento activo | C11: =IF('01 Enero'!E12="","",'01 Enero'!E12) | D11: =IF('02 Febrero'!E12="","",'02 Febrero'!E12) | E11: =IF('03 Marzo'!E12="","",'03 Marzo'!E12) | F11: =IF('04 Abril'!E12="","",'04 Abril'!E12) | G11: =IF('05 Mayo'!E12="","",'05 Mayo'!E12) | H11: =IF('06 Junio'!E12="","",'06 Junio'!E12) | I11: =IF('07 Julio'!E12="","",'07 Julio'!E12) | J11: =IF('08 Agosto'!E12="","",'08 Agosto'!E12) | K11: =IF('09 Septiembre'!E12="","",'09 Septiembre'!E12) | L11: =IF('10 Octubre'!E12="","",'10 Octubre'!E12) | M11: =IF('11 Noviembre'!E12="","",'11 Noviembre'!E12) | N11: =IF('12 Diciembre'!E12="","",'12 Diciembre'!E12) | O11: =COUNT(C11:N11) -> 0 | P11: =IFERROR(INDEX(C11:N11,MATCH(TRUE(),INDEX(C11:N11<>"",0),0)),"") | Q11: =IFERROR(LOOKUP(9.99E+307,C11:N11),"") | R11: =IF(O11<2,"—",IF(Q11=P11,"Estable",IF(Q11>P11,"Mejora","Empeora"))) -> —
A12: 8 | B12: Captación por recomendación | C12: =IF('01 Enero'!E13="","",'01 Enero'!E13) | D12: =IF('02 Febrero'!E13="","",'02 Febrero'!E13) | E12: =IF('03 Marzo'!E13="","",'03 Marzo'!E13) | F12: =IF('04 Abril'!E13="","",'04 Abril'!E13) | G12: =IF('05 Mayo'!E13="","",'05 Mayo'!E13) | H12: =IF('06 Junio'!E13="","",'06 Junio'!E13) | I12: =IF('07 Julio'!E13="","",'07 Julio'!E13) | J12: =IF('08 Agosto'!E13="","",'08 Agosto'!E13) | K12: =IF('09 Septiembre'!E13="","",'09 Septiembre'!E13) | L12: =IF('10 Octubre'!E13="","",'10 Octubre'!E13) | M12: =IF('11 Noviembre'!E13="","",'11 Noviembre'!E13) | N12: =IF('12 Diciembre'!E13="","",'12 Diciembre'!E13) | O12: =COUNT(C12:N12) -> 0 | P12: =IFERROR(INDEX(C12:N12,MATCH(TRUE(),INDEX(C12:N12<>"",0),0)),"") | Q12: =IFERROR(LOOKUP(9.99E+307,C12:N12),"") | R12: =IF(O12<2,"—",IF(Q12=P12,"Estable",IF(Q12>P12,"Mejora","Empeora"))) -> —
A13: 9 | B13: Ofrecimiento del programa de cuidado | C13: =IF('01 Enero'!E14="","",'01 Enero'!E14) | D13: =IF('02 Febrero'!E14="","",'02 Febrero'!E14) | E13: =IF('03 Marzo'!E14="","",'03 Marzo'!E14) | F13: =IF('04 Abril'!E14="","",'04 Abril'!E14) | G13: =IF('05 Mayo'!E14="","",'05 Mayo'!E14) | H13: =IF('06 Junio'!E14="","",'06 Junio'!E14) | I13: =IF('07 Julio'!E14="","",'07 Julio'!E14) | J13: =IF('08 Agosto'!E14="","",'08 Agosto'!E14) | K13: =IF('09 Septiembre'!E14="","",'09 Septiembre'!E14) | L13: =IF('10 Octubre'!E14="","",'10 Octubre'!E14) | M13: =IF('11 Noviembre'!E14="","",'11 Noviembre'!E14) | N13: =IF('12 Diciembre'!E14="","",'12 Diciembre'!E14) | O13: =COUNT(C13:N13) -> 0 | P13: =IFERROR(INDEX(C13:N13,MATCH(TRUE(),INDEX(C13:N13<>"",0),0)),"") | Q13: =IFERROR(LOOKUP(9.99E+307,C13:N13),"") | R13: =IF(O13<2,"—",IF(Q13=P13,"Estable",IF(Q13>P13,"Mejora","Empeora"))) -> —
A14: 10 | B14: Auditorías ejecutadas en fecha | C14: =IF('01 Enero'!E15="","",'01 Enero'!E15) | D14: =IF('02 Febrero'!E15="","",'02 Febrero'!E15) | E14: =IF('03 Marzo'!E15="","",'03 Marzo'!E15) | F14: =IF('04 Abril'!E15="","",'04 Abril'!E15) | G14: =IF('05 Mayo'!E15="","",'05 Mayo'!E15) | H14: =IF('06 Junio'!E15="","",'06 Junio'!E15) | I14: =IF('07 Julio'!E15="","",'07 Julio'!E15) | J14: =IF('08 Agosto'!E15="","",'08 Agosto'!E15) | K14: =IF('09 Septiembre'!E15="","",'09 Septiembre'!E15) | L14: =IF('10 Octubre'!E15="","",'10 Octubre'!E15) | M14: =IF('11 Noviembre'!E15="","",'11 Noviembre'!E15) | N14: =IF('12 Diciembre'!E15="","",'12 Diciembre'!E15) | O14: =COUNT(C14:N14) -> 0 | P14: =IFERROR(INDEX(C14:N14,MATCH(TRUE(),INDEX(C14:N14<>"",0),0)),"") | Q14: =IFERROR(LOOKUP(9.99E+307,C14:N14),"") | R14: =IF(O14<2,"—",IF(Q14=P14,"Estable",IF(Q14>P14,"Mejora","Empeora"))) -> —
B16: El indicador 5 mide euros, no porcentaje: su tendencia «Mejora» significa que el producto pendiente baja.

Sheet Los cinco números
A1: Los cinco números que aún no tenemos
A2: apartado 7 del Plan de Dirección. Rellénense las casillas amarillas; los cinco resultados se calculan solos. Hasta que estén, cualquier objetivo comercial es una opinión.
B4: Entradas
B5: Costes fijos mensuales | E5: Nóminas, alquiler, suministros, seguros, cuotas y amortizaciones. Día 15.
B6: Margen de contribución sobre venta | C6: 0.4 | E6: Supuesto de trabajo del apartado 18 mientras no haya escandallo propio.
B7: Ticket medio del caso aceptado | C7: 1800 | E7: Supuesto de trabajo del apartado 18. Se sustituye por el real.
B8: Tasa de conversión de la primera visita | C8: 0.45 | E8: Enlaza con el indicador 6 en cuanto haya tres meses de serie.
B9: Días laborables al mes | C9: 21 | E9: Parámetro de capacidad.
B10: Tesorería disponible | E10: Saldo libre de compromisos a fecha de corte. Día 21.
B11: Producto pendiente heredado | E11: Importe cobrado o comprometido y no ejecutado. Día 15.
B14: Resultados
B15: 1 · Costes fijos mensuales | C15: =IF(C5="","pendiente",C5) -> pendiente | E15: El primero de los cinco. Sin él no hay ninguno de los demás.
B16: 2 · Punto de equilibrio mensual | C16: =IF(OR(C5="",C6=0),"pendiente",C5/C6) -> pendiente | E16: Facturación mensual necesaria para cubrir los costes fijos, dado el margen de contribución.
B17: 3 · Primeras visitas necesarias al día | C17: =IF(OR(C15="",C16="pendiente",C7=0,C8=0,C9=0),"pendiente",C16/(C8*C7)/C9) -> pendiente | E17: Cuántas primeras visitas diarias hacen falta para llegar al equilibrio con la conversión y el ticket actuales.
B18: 4 · Producto pendiente heredado | C18: =IF(C11="","pendiente",C11) -> pendiente | E18: Caja ya cobrada que hay que convertir en producción. Es la palanca 1 del apartado 14.
B19: 5 · Meses de colchón de tesorería | C19: =IF(OR(C10="",C5="",C5=0),"pendiente",C10/C5) -> pendiente | E19: Cuántos meses aguanta el centro sin ingresar nada. Por debajo de tres, es un riesgo de Junta.
B21: Los resultados dicen «pendiente» mientras falte alguna entrada. Es deliberado: un número inventado es peor que un hueco declarado.
